mark_sideways/__init__.py
mark_sideways/cli.py
mark_sideways-0.4.1.dist-info/METADATA
mark_sideways-0.4.1.dist-info/WHEEL
mark_sideways-0.4.1.dist-info/entry_points.txt
mark_sideways-0.4.1.dist-info/licenses/LICENSE
mark_sideways-0.4.1.dist-info/RECORD
