Metadata-Version: 2.4
Name: mark-sideways
Version: 0.4.1
Summary: Render markdown in the terminal
License-Expression: MIT
License-File: LICENSE
Author: chris48s
Requires-Python: >=3.10
Classifier: Programming Language :: Python :: 3
Classifier: Programming Language :: Python :: 3.10
Classifier: Programming Language :: Python :: 3.11
Classifier: Programming Language :: Python :: 3.12
Classifier: Programming Language :: Python :: 3.13
Classifier: Programming Language :: Python :: 3.14
Requires-Dist: rich (>=10.2.0)
Project-URL: Home, https://github.com/chris48s/mark-sideways
Project-URL: Source, https://github.com/chris48s/mark-sideways
